cloudmunch
