Metadata-Version: 1.1
Name: cloudmunch-cli
Version: 0.5.3
Summary: CloudMunch CLI is a tool for working with CloudMunch Platform
Home-page: UNKNOWN
Author: Cloudmunch Inc.
Author-email: info@cloudmunch.com
License: UNKNOWN
Platform: UNKNOWN
Classifier: Development Status :: 4 - Beta
Classifier: Environment :: Console
Classifier: Intended Audience :: Developers
Classifier: Intended Audience :: System Administrators
Classifier: Programming Language :: Python
